[
  {
    "id": "wechat_21836644f23d",
    "platform": "wechat",
    "title": "MUMO木墨:不妥协的生意,不被规训的人",
    "author": "腾讯网",
    "publishedAt": "2026-03-26T00:00:00",
    "url": "https://mp.weixin.qq.com/s?__biz=MzU2NTExMjQ4Nw==&mid=2247542008&idx=1&sn=cf70c97a9c3862e3a83da846da9ad1ad&chksm=fd349b9868c7dc90117e75737e49e5ea5ebe05279b6aecb9ea1daa99fcd8e565e68b0ffab655&scene=27",
    "summary": " 上一周,我们记录了景德镇的乐天陶社——一个通过市集、驻场与教育项目慢慢影响城市文化氛围的实践。 而另一种“个性企业”的探索,则发生在一家家具品牌里。MUMO 木墨,这家创立于2011 年的品牌,一度赶上电商时代的高速增长,却始终对“规模”和“流量”保持某种距离:不参与“双11”、设置长期价格保护、在增长与价值观之间不断权衡。与此同时,它也在尝试让一家企业不仅围绕增长运转,而是与劳动、创作和日常生活发生更多连接。 在“共益企业庆祝月” 即将结束之际,我们把视线落在这样一家企业身上——它的故事或许不是关于如何成为一家更大的公司,而是关于:一家企业如何决定自己想成为什么样的企业。 产品会自然呈现它",
    "likes": 0,
    "comments": 0,
    "collectors": 0,
    "keywords": [
      "木墨"
    ],
    "brand": "木墨",
    "fetchedAt": "2026-04-01T08:02:27.716543",
    "enriched": true,
    "note": "Enrichment attempted",
    "enrichedAt": "2026-04-01T08:03:26.637700"
  },
  {
    "id": "wechat_5469e635151a",
    "platform": "wechat",
    "title": "学术丨巴蜀地区明代木构建筑研究价值及营造学社相关研究初探",
    "author": "腾讯网",
    "publishedAt": "2023-01-11T00:00:00",
    "url": "https://mp.weixin.qq.com/s?__biz=MzI2NjE3NDgxMw==&mid=2247489407&idx=1&sn=c40c0ea1ae3126583d8d64b373b59c7f&chksm=ea937f4ddde4f65ba205c679c738256949a74c014971c17c3a2ac378bd71e40f84a8e1a44b9c&scene=27",
    "summary": " 立足中国建筑史研究,探索中国建筑发展规律,为当前建筑实践提供借鉴,促进建筑史学术研究成果传播,提高我国建筑领域的学术水平和国际影响力。 本文刊发于《建筑史学刊》2022年第3期 《巴蜀地区明代木构建筑研究价值及营造学社相关研究初探——兼论巴蜀地区明代木构建筑研究现状及展望》一文聚焦于巴蜀地区明代木构建筑研究的学术史,尤其着重回顾了营造学社对30余处明代木构建筑的研究,认为其奠定了巴蜀明代木构建筑研究的基础,文章同时指出巴蜀明代木构的特殊价值、研究现状以及有待开展的课题。 在巴蜀传统建筑研究中,明代木构建筑在很长一段时间内并没有得到足够重视,缺乏系统而有深度的研究。导致这一现象的可能原因笔者认",
    "likes": 0,
    "comments": 0,
    "collectors": 0,
    "keywords": [
      "明时木作"
    ],
    "brand": null,
    "fetchedAt": "2026-04-01T08:02:32.393027",
    "enriched": true,
    "note": "Enrichment attempted",
    "enrichedAt": "2026-04-01T08:03:41.689505"
  },
  {
    "id": "wechat_2c74c590ce21",
    "platform": "wechat",
    "title": "“全屋定制”甲醛超标 耐心调解保障“安心入住” ",
    "author": "腾讯网",
    "publishedAt": "2024-02-04T00:00:00",
    "url": "https://mp.weixin.qq.com/s?__biz=MzIzMTU1OTIxNg==&mid=2247531240&idx=2&sn=f8a631b6762456dbdc5415e2d96c7502&chksm=e8a063b7dfd7eaa1c909ac93192e0b72e59e2bd14c20038c95cb978b436b41626e53ee93ffc1&scene=27",
    "summary": " 甲醛超标起纠纷 黄某向某商家定制了全套衣柜,由该商家负责安装到黄某购买的新居中。黄某依约支付了费用,该商家也按约完成了安装。可安装完衣柜后,黄某总能闻到刺鼻的味道,在房间待久了还会觉得头晕目眩。黄某怀疑是定制家具甲醛超标,遂找到该商家讨说法。 2023年8月,双方在漳州市芗城区市场监管局调解下签订《投诉调解书》,达成协议,双方同意将衣柜板材交由专业检测机构检验。根据检测报告,定制衣柜甲醛超过国家甲醛含量安全标准。黄某联系该商家协商未果,故而成讼,要求家具店更换全部柜体并赔偿损失。 耐心寻找“最优解” 收到案件后,经办法官许雅燕认为案件关系到当事人健康安心居住的切身利益,调解解决可能会是“最优",
    "likes": 0,
    "comments": 0,
    "collectors": 0,
    "keywords": [
      "全屋定制 甲醛"
    ],
    "brand": null,
    "fetchedAt": "2026-04-01T08:02:59.992117",
    "enriched": true,
    "note": "Enrichment attempted",
    "enrichedAt": "2026-04-01T08:03:58.913052"
  }
]